easy_eda/__init__.py
easy_eda-0.1.10.dist-info/DESCRIPTION.rst
easy_eda-0.1.10.dist-info/METADATA
easy_eda-0.1.10.dist-info/RECORD
easy_eda-0.1.10.dist-info/WHEEL
easy_eda-0.1.10.dist-info/metadata.json
easy_eda-0.1.10.dist-info/top_level.txt
