Metadata-Version: 2.0
Name: easy-eda
Version: 0.1.10
Summary: Exploratory Data Analysis
Home-page: http://github.com/miskolc/easy_eda
Author: Dragos Calin
Author-email: dragos.calin.gm@mail.com
License: MIT
Platform: UNKNOWN
Requires-Dist: matplotlib (>=2.2.3)
Requires-Dist: numpy (>=1.15.1)
Requires-Dist: pandas (>=0.22.0)
Requires-Dist: seaborn (>=0.9.0)
